openhands/workspace/__init__.py
openhands/workspace/py.typed
openhands/workspace/apptainer/__init__.py
openhands/workspace/apptainer/workspace.py
openhands/workspace/cloud/__init__.py
openhands/workspace/cloud/workspace.py
openhands/workspace/docker/__init__.py
openhands/workspace/docker/dev_workspace.py
openhands/workspace/docker/workspace.py
openhands/workspace/remote_api/__init__.py
openhands/workspace/remote_api/workspace.py
openhands_workspace-1.10.0.dist-info/METADATA
openhands_workspace-1.10.0.dist-info/WHEEL
openhands_workspace-1.10.0.dist-info/top_level.txt
openhands_workspace-1.10.0.dist-info/RECORD
